django_excel_extract-1.0.0.dist-info/licenses/LICENSE
excel_extract/__init__.py
excel_extract/excel.py
excel_extract/processors.py
excel_extract/response.py
django_excel_extract-1.0.0.dist-info/METADATA
django_excel_extract-1.0.0.dist-info/WHEEL
django_excel_extract-1.0.0.dist-info/top_level.txt
django_excel_extract-1.0.0.dist-info/RECORD
