Metadata-Version: 2.4
Name: django-excel-extract
Version: 1.0.0
Summary: Django queryset Excel extraction
Home-page: https://github.com/DmitryTok/django-excel-extract
Author: Dmytry Tokariev
Author-email: moon0939110824@gmail.com
License: MIT
Classifier: Programming Language :: Python :: 3
Classifier: Framework :: Django
Classifier: License :: OSI Approved :: MIT License
Classifier: Operating System :: OS Independent
Requires-Python: >=3.9
License-File: LICENSE
Requires-Dist: django>=4.2.7
Requires-Dist: openpyxl>=3.1.5
Requires-Dist: pandas>=2.2.3
Dynamic: license-file
